{
    "decimal_data": [
        {
            "movement_direction": 2,
            "speed": 0,
            "pos_x": 0,
            "pos_y": 0,
            "w": 0,
            "h": 0,
            "wait_time": 0,
            "destroy_time": 0,
            "destroy_trigger": 0,
            "free(unused)": 0
        },
        {
            "movement_direction": 1,
            "speed": 0,
            "pos_x": 0,
            "pos_y": 0,
            "w": 0,
            "h": 0,
            "wait_time": 1,
            "destroy_time": 5,
            "destroy_trigger": 0,
            "free(unused)": 0
        },
        {
            "movement_direction": 1,
            "speed": 0,
            "pos_x": 0,
            "pos_y": 0,
            "w": 0,
            "h": 0,
            "wait_time": 1,
            "destroy_time": 5,
            "destroy_trigger": 0,
            "free(unused)": 0
        },
        {
            "movement_direction": 2,
            "speed": 6,
            "pos_x": 137,
            "pos_y": 328,
            "w": 62,
            "h": 12,
            "wait_time": 3,
            "destroy_time": 10,
            "destroy_trigger": 2,
            "free(unused)": 0
        },
        {
            "movement_direction": 2,
            "speed": 9,
            "pos_x": 137,
            "pos_y": 328,
            "w": 62,
            "h": 12,
            "wait_time": 1.5,
            "destroy_time": 10,
            "destroy_trigger": 2,
            "free(unused)": 0
        },
        {
            "movement_direction": 2,
            "speed": 9,
            "pos_x": 137,
            "pos_y": 328,
            "w": 62,
            "h": 12,
            "wait_time": 1.5,
            "destroy_time": 10,
            "destroy_trigger": 2,
            "free(unused)": 0
        },
        {
            "movement_direction": 2,
            "speed": 9,
            "pos_x": 137,
            "pos_y": 328,
            "w": 62,
            "h": 12,
            "wait_time": 1.5,
            "destroy_time": 10,
            "destroy_trigger": 2,
            "free(unused)": 0
        },
        {
            "movement_direction": 2,
            "speed": 9,
            "pos_x": 137,
            "pos_y": 328,
            "w": 62,
            "h": 12,
            "wait_time": 1.5,
            "destroy_time": 10,
            "destroy_trigger": 2,
            "free(unused)": 0
        },
        {
            "movement_direction": 2,
            "speed": 9,
            "pos_x": 137,
            "pos_y": 328,
            "w": 62,
            "h": 12,
            "wait_time": 1.5,
            "destroy_time": 10,
            "destroy_trigger": 2,
            "free(unused)": 0
        },
        {
            "movement_direction": 1,
            "speed": 2,
            "pos_x": 0,
            "pos_y": 0,
            "w": 0,
            "h": 0,
            "wait_time": 1,
            "destroy_time": 5,
            "destroy_trigger": 0,
            "free(unused)": 0
        },
        {
            "movement_direction": 2,
            "speed": 4,
            "pos_x": 137,
            "pos_y": 328,
            "w": 42,
            "h": 12,
            "wait_time": 3,
            "destroy_time": 25.5,
            "destroy_trigger": 2,
            "free(unused)": 0
        },
        {
            "movement_direction": 2,
            "speed": 4,
            "pos_x": 137,
            "pos_y": 328,
            "w": 42,
            "h": 12,
            "wait_time": 3,
            "destroy_time": 25.5,
            "destroy_trigger": 2,
            "free(unused)": 0
        },
        {
            "movement_direction": 2,
            "speed": 4,
            "pos_x": 137,
            "pos_y": 328,
            "w": 42,
            "h": 12,
            "wait_time": 3,
            "destroy_time": 25.5,
            "destroy_trigger": 2,
            "free(unused)": 0
        },
        {
            "movement_direction": 2,
            "speed": 4,
            "pos_x": 137,
            "pos_y": 328,
            "w": 42,
            "h": 12,
            "wait_time": 3,
            "destroy_time": 25.5,
            "destroy_trigger": 2,
            "free(unused)": 0
        },
        {
            "movement_direction": 2,
            "speed": 4,
            "pos_x": 137,
            "pos_y": 328,
            "w": 42,
            "h": 12,
            "wait_time": 3,
            "destroy_time": 25.5,
            "destroy_trigger": 2,
            "free(unused)": 0
        },
        {
            "movement_direction": 2,
            "speed": 4,
            "pos_x": 137,
            "pos_y": 328,
            "w": 42,
            "h": 12,
            "wait_time": 3,
            "destroy_time": 25.5,
            "destroy_trigger": 2,
            "free(unused)": 0
        }
    ]
}