{
    "game_manger": {
        "stage": 1,
        "attack_amount": 24,
        "platform_amount": 1,
        "wait_time": 5,
        "gravity_direction": 0,
        "display_pos_x1": 245,
        "display_pos_y1": 229,
        "display_pos_x2": 403,
        "display_pos_y2": 386,
        "free(unused)": 0
    },

    "attack_object":[
        {
            "type": 0, 
            "colider_type": 0, 
            "movement_direction": 2, 
            "speed": 6, 
            "pos_x": 245, 
            "pos_y": 314, 
            "w": 12, 
            "h": 72, 
            "wait_time": 0.1, 
            "destroy_time": 10,
            "destroy_trigger": 2,
            "free(unused)": 0
        },

        {
            "type": 0, 
            "colider_type": 0, 
            "movement_direction": 2, 
            "speed": 6, 
            "pos_x": 245, 
            "pos_y": 229, 
            "w": 12, 
            "h": 46, 
            "wait_time": 0.7, 
            "destroy_time": 10,
            "destroy_trigger": 2,
            "free(unused)": 0
        },



        {
            "type": 0, 
            "colider_type": 0, 
            "movement_direction": 2, 
            "speed": 6, 
            "pos_x": 245, 
            "pos_y": 310, 
            "w": 12, 
            "h": 76, 
            "wait_time": 0.1, 
            "destroy_time": 10,
            "destroy_trigger": 2,
            "free(unused)": 0
        },

        {
            "type": 0, 
            "colider_type": 0, 
            "movement_direction": 2, 
            "speed": 6, 
            "pos_x": 245, 
            "pos_y": 229, 
            "w": 12, 
            "h": 42, 
            "wait_time": 0.7, 
            "destroy_time": 10,
            "destroy_trigger": 2,
            "free(unused)": 0
        },


        {
            "type": 0, 
            "colider_type": 0, 
            "movement_direction": 2, 
            "speed": 6, 
            "pos_x": 245, 
            "pos_y": 306, 
            "w": 12, 
            "h": 80, 
            "wait_time": 0.1, 
            "destroy_time": 10,
            "destroy_trigger": 2,
            "free(unused)": 0
        },

        {
            "type": 0, 
            "colider_type": 0, 
            "movement_direction": 2, 
            "speed": 6, 
            "pos_x": 245, 
            "pos_y": 229, 
            "w": 12, 
            "h": 38, 
            "wait_time": 0.7, 
            "destroy_time": 10,
            "destroy_trigger": 2,
            "free(unused)": 0
        },



        {
            "type": 0, 
            "colider_type": 0, 
            "movement_direction": 2, 
            "speed": 6, 
            "pos_x": 245, 
            "pos_y": 302, 
            "w": 12, 
            "h": 84, 
            "wait_time": 0.1, 
            "destroy_time": 10,
            "destroy_trigger": 2,
            "free(unused)": 0
        },

        {
            "type": 0, 
            "colider_type": 0, 
            "movement_direction": 2, 
            "speed": 6, 
            "pos_x": 245, 
            "pos_y": 229, 
            "w": 12, 
            "h": 34, 
            "wait_time": 0.7, 
            "destroy_time": 10,
            "destroy_trigger": 2,
            "free(unused)": 0
        },



        {
            "type": 0, 
            "colider_type": 0, 
            "movement_direction": 2, 
            "speed": 6, 
            "pos_x": 245, 
            "pos_y": 298, 
            "w": 12, 
            "h": 88, 
            "wait_time": 0.1, 
            "destroy_time": 10,
            "destroy_trigger": 2,
            "free(unused)": 0
        },

        {
            "type": 0, 
            "colider_type": 0, 
            "movement_direction": 2, 
            "speed": 6, 
            "pos_x": 245, 
            "pos_y": 229, 
            "w": 12, 
            "h": 30, 
            "wait_time": 0.7, 
            "destroy_time": 10,
            "destroy_trigger": 2,
            "free(unused)": 0
        },




        {
            "type": 0, 
            "colider_type": 0, 
            "movement_direction": 2, 
            "speed": 6, 
            "pos_x": 245, 
            "pos_y": 294, 
            "w": 12, 
            "h": 92, 
            "wait_time": 0.1, 
            "destroy_time": 10,
            "destroy_trigger": 2,
            "free(unused)": 0
        },

        {
            "type": 0, 
            "colider_type": 0, 
            "movement_direction": 2, 
            "speed": 6, 
            "pos_x": 245, 
            "pos_y": 229, 
            "w": 12, 
            "h": 26, 
            "wait_time": 0.7, 
            "destroy_time": 10,
            "destroy_trigger": 2,
            "free(unused)": 0
        },



        {
            "type": 0, 
            "colider_type": 0, 
            "movement_direction": 2, 
            "speed": 6, 
            "pos_x": 245, 
            "pos_y": 290, 
            "w": 12, 
            "h": 96, 
            "wait_time": 0.1, 
            "destroy_time": 10,
            "destroy_trigger": 2,
            "free(unused)": 0
        },

        {
            "type": 0, 
            "colider_type": 0, 
            "movement_direction": 2, 
            "speed": 6, 
            "pos_x": 245, 
            "pos_y": 229, 
            "w": 12, 
            "h": 22, 
            "wait_time": 0.7, 
            "destroy_time": 10,
            "destroy_trigger": 2,
            "free(unused)": 0
        },



        {
            "type": 0, 
            "colider_type": 0, 
            "movement_direction": 2, 
            "speed": 6, 
            "pos_x": 245, 
            "pos_y": 286, 
            "w": 12, 
            "h": 100, 
            "wait_time": 0.1, 
            "destroy_time": 10,
            "destroy_trigger": 2,
            "free(unused)": 0
        },

        {
            "type": 0, 
            "colider_type": 0, 
            "movement_direction": 2, 
            "speed": 6, 
            "pos_x": 245, 
            "pos_y": 229, 
            "w": 12, 
            "h": 18, 
            "wait_time": 0.7, 
            "destroy_time": 10,
            "destroy_trigger": 2,
            "free(unused)": 0
        },



        {
            "type": 0, 
            "colider_type": 0, 
            "movement_direction": 2, 
            "speed": 6, 
            "pos_x": 245, 
            "pos_y": 290, 
            "w": 12, 
            "h": 96, 
            "wait_time": 0.1, 
            "destroy_time": 10,
            "destroy_trigger": 2,
            "free(unused)": 0
        },

        {
            "type": 0, 
            "colider_type": 0, 
            "movement_direction": 2, 
            "speed": 6, 
            "pos_x": 245, 
            "pos_y": 229, 
            "w": 12, 
            "h": 22, 
            "wait_time": 0.7, 
            "destroy_time": 10,
            "destroy_trigger": 2,
            "free(unused)": 0
        },



        {
            "type": 0, 
            "colider_type": 0, 
            "movement_direction": 2, 
            "speed": 6, 
            "pos_x": 245, 
            "pos_y": 294, 
            "w": 12, 
            "h": 92, 
            "wait_time": 0.1, 
            "destroy_time": 10,
            "destroy_trigger": 2,
            "free(unused)": 0
        },

        {
            "type": 0, 
            "colider_type": 0, 
            "movement_direction": 2, 
            "speed": 6, 
            "pos_x": 245, 
            "pos_y": 229, 
            "w": 12, 
            "h": 26, 
            "wait_time": 0.7, 
            "destroy_time": 10,
            "destroy_trigger": 2,
            "free(unused)": 0
        },




        {
            "type": 0, 
            "colider_type": 0, 
            "movement_direction": 2, 
            "speed": 6, 
            "pos_x": 245, 
            "pos_y": 298, 
            "w": 12, 
            "h": 88, 
            "wait_time": 0.1, 
            "destroy_time": 10,
            "destroy_trigger": 2,
            "free(unused)": 0
        },

        {
            "type": 0, 
            "colider_type": 0, 
            "movement_direction": 2, 
            "speed": 6, 
            "pos_x": 245, 
            "pos_y": 229, 
            "w": 12, 
            "h": 30, 
            "wait_time": 0.7, 
            "destroy_time": 10,
            "destroy_trigger": 2,
            "free(unused)": 0
        },


        {
            "type": 0, 
            "colider_type": 0, 
            "movement_direction": 2, 
            "speed": 6, 
            "pos_x": 245, 
            "pos_y": 302, 
            "w": 12, 
            "h": 84, 
            "wait_time": 0.1, 
            "destroy_time": 10,
            "destroy_trigger": 2,
            "free(unused)": 0
        },

        {
            "type": 0, 
            "colider_type": 0, 
            "movement_direction": 2, 
            "speed": 6, 
            "pos_x": 245, 
            "pos_y": 229, 
            "w": 12, 
            "h": 34, 
            "wait_time": 0.7, 
            "destroy_time": 10,
            "destroy_trigger": 2,
            "free(unused)": 0
        }
        

    ],

    "platform_object": [
        {
            "movement_direction": 1, 
            "speed": 0, 
            "pos_x": 0, 
            "pos_y": 0, 
            "w": 0, 
            "h": 0, 
            "wait_time": 1, 
            "destroy_time": 5,
            "destroy_trigger": 0,
            "free(unused)": 0
        }
    ]
}